sage_agent/__init__.py
sage_agent/_version.py
sage_agent-0.5.1.data/data/share/jupyter/labextensions/sage-agent/package.json
sage_agent-0.5.1.data/data/share/jupyter/labextensions/sage-agent/schemas/sage-agent/package.json.orig
sage_agent-0.5.1.data/data/share/jupyter/labextensions/sage-agent/schemas/sage-agent/plugin.json
sage_agent-0.5.1.data/data/share/jupyter/labextensions/sage-agent/static/122.38bc3343ed326a730d37.js
sage_agent-0.5.1.data/data/share/jupyter/labextensions/sage-agent/static/220.32596efbd8b69fd4d1cd.js
sage_agent-0.5.1.data/data/share/jupyter/labextensions/sage-agent/static/262.b0b5ee3d89f3c9afe174.js
sage_agent-0.5.1.data/data/share/jupyter/labextensions/sage-agent/static/353.5171142ab707a0c6199c.js
sage_agent-0.5.1.data/data/share/jupyter/labextensions/sage-agent/static/363.0079887b65191351f33d.js
sage_agent-0.5.1.data/data/share/jupyter/labextensions/sage-agent/static/364.06a53bcde0aaca8cd382.js
sage_agent-0.5.1.data/data/share/jupyter/labextensions/sage-agent/static/439.d0df468f61a1cec58eaa.js
sage_agent-0.5.1.data/data/share/jupyter/labextensions/sage-agent/static/45.2c53a5b0fa7025b8d1ca.js
sage_agent-0.5.1.data/data/share/jupyter/labextensions/sage-agent/static/481.177e8cfeae20755d1a3d.js
sage_agent-0.5.1.data/data/share/jupyter/labextensions/sage-agent/static/553.f1ef419b78627ab4bb0a.js
sage_agent-0.5.1.data/data/share/jupyter/labextensions/sage-agent/static/553.f1ef419b78627ab4bb0a.js.LICENSE.txt
sage_agent-0.5.1.data/data/share/jupyter/labextensions/sage-agent/static/635.a18bb125b30541868060.js
sage_agent-0.5.1.data/data/share/jupyter/labextensions/sage-agent/static/713.2638a110416800073e26.js
sage_agent-0.5.1.data/data/share/jupyter/labextensions/sage-agent/static/742.62e5cd6f4da630580cbd.js
sage_agent-0.5.1.data/data/share/jupyter/labextensions/sage-agent/static/747.3b0e635a3375a1e97c2b.js
sage_agent-0.5.1.data/data/share/jupyter/labextensions/sage-agent/static/821.fe1c2fb428cefe29438b.js
sage_agent-0.5.1.dist-info/METADATA
sage_agent-0.5.1.dist-info/WHEEL
sage_agent-0.5.1.dist-info/licenses/LICENSE
sage_agent-0.5.1.dist-info/RECORD
